{
    "keep": {
        "days": true,
        "amount": 14
    },
    "auditLog": "D:\\Next 2.0\\3 Be a NoSQL Backend Braniac\\15 Compleate Student Model, implement transaction and rollback, practice faculty Model\\logs\\winston\\error\\.da428718f4c0f692e2b1bd3bde5f9f98a96a188e-audit.json",
    "files": [
        {
            "date": 1727840856804,
            "name": "D:\\Next 2.0\\3 Be a NoSQL Backend Braniac\\15 Compleate Student Model, implement transaction and rollback, practice faculty Model\\logs\\winston\\error\\un-2024-02-10-09-error.log",
            "hash": "8f29cda8182c81e67b8f6dd17529330aa115f7066212257d634acf0827e3bebd"
        },
        {
            "date": 1727841653022,
            "name": "D:\\Next 2.0\\3 Be a NoSQL Backend Braniac\\15 Compleate Student Model, implement transaction and rollback, practice faculty Model\\logs\\winston\\error\\un-2024-02-10-10-error.log",
            "hash": "1963f7f500f0f054c1deb06dd1cc829fe4783d6dc96e447f388a94c0848c5a93"
        },
        {
            "date": 1727845749052,
            "name": "D:\\Next 2.0\\3 Be a NoSQL Backend Braniac\\15 Compleate Student Model, implement transaction and rollback, practice faculty Model\\logs\\winston\\error\\un-2024-02-10-11-error.log",
            "hash": "a3410eda27531b1fedc32f166a679a2f6e8ef525585ceada35c0263f191a68ed"
        },
        {
            "date": 1727849765715,
            "name": "D:\\Next 2.0\\3 Be a NoSQL Backend Braniac\\15 Compleate Student Model, implement transaction and rollback, practice faculty Model\\logs\\winston\\error\\un-2024-02-10-12-error.log",
            "hash": "143dc24b8539bdd347797e2f7f12f9593f91814b78084fd526dff64833d902b5"
        },
        {
            "date": 1727964665439,
            "name": "D:\\Next 2.0\\3 Be a NoSQL Backend Braniac\\15 Compleate Student Model, implement transaction and rollback, practice faculty Model\\logs\\winston\\error\\un-2024-03-10-20-error.log",
            "hash": "b0255c7e14586e0f36b23f517ee512137290d77635672c9bbcaa7fa8a902d5e5"
        },
        {
            "date": 1727967612512,
            "name": "D:\\Next 2.0\\3 Be a NoSQL Backend Braniac\\15 Compleate Student Model, implement transaction and rollback, practice faculty Model\\logs\\winston\\error\\un-2024-03-10-21-error.log",
            "hash": "e31e8a8553a370d86531da3e3e487326c0e299801360c0b5d2287efcc712411d"
        },
        {
            "date": 1727978071907,
            "name": "D:\\Next 2.0\\3 Be a NoSQL Backend Braniac\\15 Compleate Student Model, implement transaction and rollback, practice faculty Model\\logs\\winston\\error\\un-2024-03-10-23-error.log",
            "hash": "4bc6731eea1ceceeb1870d22e08d8ffafbb673acd1ce42a85df7385f4d98c78e"
        },
        {
            "date": 1727978520862,
            "name": "D:\\Next 2.0\\3 Be a NoSQL Backend Braniac\\15 Compleate Student Model, implement transaction and rollback, practice faculty Model\\logs\\winston\\error\\un-2024-04-10-00-error.log",
            "hash": "e37f1672dd7f0ff5134503a79a1d74ca57715c409072a517aae2779fb3c1b8e9"
        },
        {
            "date": 1727982222710,
            "name": "D:\\Next 2.0\\3 Be a NoSQL Backend Braniac\\15 Compleate Student Model, implement transaction and rollback, practice faculty Model\\logs\\winston\\error\\un-2024-04-10-01-error.log",
            "hash": "0e1753e60d9cb5cb158f44b7da41f9807a8aefbdb5bec9dece435602ffaac77e"
        },
        {
            "date": 1728021339983,
            "name": "D:\\Next 2.0\\3 Be a NoSQL Backend Braniac\\15 Compleate Student Model, implement transaction and rollback, practice faculty Model\\logs\\winston\\error\\un-2024-04-10-11-error.log",
            "hash": "8502def213c3be32fb4afdaf1f8c813e44e45a9b4b397f9c23c74ec0a9ad86a3"
        },
        {
            "date": 1728021647541,
            "name": "D:\\Next 2.0\\3 Be a NoSQL Backend Braniac\\15 Compleate Student Model, implement transaction and rollback, practice faculty Model\\logs\\winston\\error\\un-2024-04-10-12-error.log",
            "hash": "e1b0a08403d3bb10c67f1130a563617a459d9181e3f50916b7b5968f1af672cb"
        },
        {
            "date": 1728055057645,
            "name": "D:\\Next 2.0\\3 Be a NoSQL Backend Braniac\\15 Compleate Student Model, implement transaction and rollback, practice faculty Model\\logs\\winston\\error\\un-2024-04-10-21-error.log",
            "hash": "469a9202de78ad04f52b79c92de4542d644023ae227992f24f7f1a9f63284e40"
        },
        {
            "date": 1728113098871,
            "name": "D:\\Next 2.0\\3 Be a NoSQL Backend Braniac\\15 Compleate Student Model, implement transaction and rollback, practice faculty Model\\logs\\winston\\error\\un-2024-05-10-13-error.log",
            "hash": "a7161c0e17b7bdd1bbec00d05bf82a2c6bd357122fd3fa82aafb295dc25d9118"
        },
        {
            "date": 1728134545605,
            "name": "D:\\Next 2.0\\3 Be a NoSQL Backend Braniac\\15 Compleate Student Model, implement transaction and rollback, practice faculty Model\\logs\\winston\\error\\un-2024-05-10-19-error.log",
            "hash": "af5f69a43b451baa95d7173c44e4c826add17e5e8cd3818cebd74d09eac39355"
        },
        {
            "date": 1728137002987,
            "name": "D:\\Next 2.0\\3 Be a NoSQL Backend Braniac\\15 Compleate Student Model, implement transaction and rollback, practice faculty Model\\logs\\winston\\error\\un-2024-05-10-20-error.log",
            "hash": "ecfe3f981c4caf52bd59915f6d88fc49064911991bdec63fb50b888fda75d134"
        },
        {
            "date": 1728140447874,
            "name": "D:\\Next 2.0\\3 Be a NoSQL Backend Braniac\\15 Compleate Student Model, implement transaction and rollback, practice faculty Model\\logs\\winston\\error\\un-2024-05-10-21-error.log",
            "hash": "7b9c7c56df51b7f05f925c24af10b83c24403a9a6e22fdea085183b4a903f96b"
        },
        {
            "date": 1728191270486,
            "name": "D:\\Next 2.0\\3 Be a NoSQL Backend Braniac\\15 Compleate Student Model, implement transaction and rollback, practice faculty Model\\logs\\winston\\error\\un-2024-06-10-11-error.log",
            "hash": "9ff0aa809b5ac959a4e839bed98dc9d636bc2ba2aaf1d5d1959b23902ec8d94e"
        },
        {
            "date": 1728194861777,
            "name": "D:\\Next 2.0\\3 Be a NoSQL Backend Braniac\\15 Compleate Student Model, implement transaction and rollback, practice faculty Model\\logs\\winston\\error\\un-2024-06-10-12-error.log",
            "hash": "6effc4435ee9486199e97b752c025264adb9de0f349de9aedb942a7b82be11f2"
        },
        {
            "date": 1728198050687,
            "name": "D:\\Next 2.0\\3 Be a NoSQL Backend Braniac\\15 Compleate Student Model, implement transaction and rollback, practice faculty Model\\logs\\winston\\error\\un-2024-06-10-13-error.log",
            "hash": "30123c0fc23a5b930f1eddd50f9dbd7c4d2ac59f8cfb1f7abcfa918a065d9d9b"
        },
        {
            "date": 1728201679970,
            "name": "D:\\Next 2.0\\3 Be a NoSQL Backend Braniac\\15 Compleate Student Model, implement transaction and rollback, practice faculty Model\\logs\\winston\\error\\un-2024-06-10-14-error.log",
            "hash": "f3b9a5251da3038775dca86728166c4d6e57f745b31f958546559d7dcebc4808"
        },
        {
            "date": 1728205277219,
            "name": "D:\\Next 2.0\\3 Be a NoSQL Backend Braniac\\15 Compleate Student Model, implement transaction and rollback, practice faculty Model\\logs\\winston\\error\\un-2024-06-10-15-error.log",
            "hash": "34eaac9e7b8d980cb029261ad2844e00084a445790115600806919b107dba414"
        }
    ],
    "hashType": "sha256"
}